napari_live_flim/__init__.py
napari_live_flim/_constants.py
napari_live_flim/_controller.py
napari_live_flim/_dataclasses.py
napari_live_flim/_flim_receiver.py
napari_live_flim/_series_viewer.py
napari_live_flim/_version.py
napari_live_flim/_widget.py
napari_live_flim/data_generator.py
napari_live_flim/gather_futures.py
napari_live_flim/napari.yaml
napari_live_flim/plot_widget.py
napari_live_flim/timing.py
napari_live_flim/_tests/__init__.py
napari_live_flim/_tests/dataclass_json.py
napari_live_flim/_tests/napari_viewer.py
napari_live_flim/_tests/simulate_acquisition.py
napari_live_flim/_tests/test_proxy_array.py
napari_live_flim/_tests/test_widget.py
napari_live_flim/colormaps/BH_compat.csv
napari_live_flim/colormaps/BH_compat_rev.csv
napari_live_flim-0.1.1.dist-info/LICENSE
napari_live_flim-0.1.1.dist-info/METADATA
napari_live_flim-0.1.1.dist-info/WHEEL
napari_live_flim-0.1.1.dist-info/entry_points.txt
napari_live_flim-0.1.1.dist-info/top_level.txt
napari_live_flim-0.1.1.dist-info/RECORD
