Metadata-Version: 2.1
Name: napari-live-flim
Version: 0.1.1
Summary: A plugin for real-time FLIM analysis
Author: Kevin Tan
Author-email: kktangent@gmail.com
License: GPL-3.0-only
Classifier: Development Status :: 2 - Pre-Alpha
Classifier: Framework :: napari
Classifier: Intended Audience :: Developers
Classifier: License :: OSI Approved :: GNU General Public License v3 (GPLv3)
Classifier: Operating System :: OS Independent
Classifier: Programming Language :: Python
Classifier: Programming Language :: Python :: 3
Classifier: Programming Language :: Python :: 3 :: Only
Classifier: Programming Language :: Python :: 3.8
Classifier: Programming Language :: Python :: 3.9
Classifier: Programming Language :: Python :: 3.10
Classifier: Topic :: Software Development :: Testing
Requires-Python: >=3.8
License-File: LICENSE
Requires-Dist: dataclasses-json
Requires-Dist: flimlib
Requires-Dist: magicgui
Requires-Dist: matplotlib
Requires-Dist: numpy
Requires-Dist: qtpy
Requires-Dist: scipy
Requires-Dist: superqt
Requires-Dist: vispy
Provides-Extra: testing
Requires-Dist: tox ; extra == 'testing'
Requires-Dist: pytest ; extra == 'testing'
Requires-Dist: pytest-cov ; extra == 'testing'
Requires-Dist: pytest-qt ; extra == 'testing'
Requires-Dist: napari ; extra == 'testing'
Requires-Dist: pyqt5 ; extra == 'testing'
